oxbuster/__init__.py
oxbuster/main.py
oxbuster-0.0.3.dist-info/METADATA
oxbuster-0.0.3.dist-info/WHEEL
oxbuster-0.0.3.dist-info/entry_points.txt
oxbuster-0.0.3.dist-info/top_level.txt
oxbuster-0.0.3.dist-info/RECORD
