Metadata-Version: 2.1
Name: oxbuster
Version: 0.0.3
Summary: A Handy Script for Finding Website Directories using Wordlists
Author: 0x68616469
Keywords: dir,buster,wordlist
Classifier: Development Status :: 4 - Beta
Classifier: Intended Audience :: Developers
Classifier: Programming Language :: Python :: 3
Classifier: Operating System :: Unix
Classifier: Operating System :: MacOS :: MacOS X
Classifier: Operating System :: Microsoft :: Windows
Requires-Dist: oxansi
Requires-Dist: oxflags
